### 前言

虽然说在Android中，我们使用枚举的地方不多，但是我们还是需要了解一下枚举在Java语言中是如何实现的。这一篇文章所用到的jdk是java 8，和以前的版本有较大差别。

### 探究枚举的实现原理

我们先写一个枚举类。

```
public enum TestEnum {

    ENUM_A("A"),
    ENUM_B("B");

    String value;

    TestEnum(String v) {
        value = v;
    }

    public String getValue() {
        return value;
    }
}

```

编译，使用javap先大概的看一下。

javap TestEnum,输入如下。

```
警告: 二进制文件TestEnum包含com.gl.TestEnum
Compiled from "TestEnum.java"
public final class com.gl.TestEnum extends java.lang.Enum<com.gl.TestEnum> {
  public static final com.gl.TestEnum ENUM_A;
  public static final com.gl.TestEnum ENUM_B;
  java.lang.String value;
  public static com.gl.TestEnum[] values();
  public static com.gl.TestEnum valueOf(java.lang.String);
  public java.lang.String getValue();
  static {};
}
```

可以看到，编译后的代码，我们的枚举继承了java.lang.Enum，并且多出了两个成员变量以及几个方法。其中static方法尤其引起我们的注意，因此，我们需要详细的看一下static方法的内容是啥。

javap -c -v TestEnum,其中，

```
  static {};
    descriptor: ()V
    flags: ACC_STATIC
    Code:
      stack=5, locals=0, args_size=0
         0: new           #4                  // class com/gl/TestEnum
         3: dup
         4: ldc           #8                  // String ENUM_A
         6: iconst_0
         7: ldc           #9                  // String A
         9: invokespecial #10                 // Method "<init>":(Ljava/lang/String;ILjava/lang/String;)V
        12: putstatic     #11                 // Field ENUM_A:Lcom/gl/TestEnum;
        15: new           #4                  // class com/gl/TestEnum
        18: dup
        19: ldc           #12                 // String ENUM_B
        21: iconst_1
        22: ldc           #13                 // String B
        24: invokespecial #10                 // Method "<init>":(Ljava/lang/String;ILjava/lang/String;)V
        27: putstatic     #14                 // Field ENUM_B:Lcom/gl/TestEnum;
        30: iconst_2
        31: anewarray     #4                  // class com/gl/TestEnum
        34: dup
        35: iconst_0
        36: getstatic     #11                 // Field ENUM_A:Lcom/gl/TestEnum;
        39: aastore
        40: dup
        41: iconst_1
        42: getstatic     #14                 // Field ENUM_B:Lcom/gl/TestEnum;
        45: aastore
        46: putstatic     #1                  // Field $VALUES:[Lcom/gl/TestEnum;
        49: return
```

从这些字节码中，可以看到，就是new 了两个TestEnum，初始化且将这个赋值给我们的两个静态变量。似乎没什么神奇的，没错，就是没什么神奇的。


