### 前言

我们都知道泛型的类型擦除。我曾经有个疑惑，就是，既然泛型有类型擦除，那么，我们为什么在运行时是可以拿到泛型的类型信息呢。今天就来看一哈。


### 举个例子

```
public class Test {

    public static void main(String[] args) {
        List<String> list = new ArrayList<>();
        for (int i = 0; i < 10; i++) {
            list.add(String.valueOf(i));
        }
        System.err.println(list.toString());
    }
}
```

接下来，我们看下这个的字节码是啥样子的。


```
{
  public com.gl.Test();
    descriptor: ()V
    flags: ACC_PUBLIC
    Code:
      stack=1, locals=1, args_size=1
         0: aload_0
         1: invokespecial #1                  // Method java/lang/Object."<init>":()V
         4: return
      LineNumberTable:
        line 9: 0
      LocalVariableTable:
        Start  Length  Slot  Name   Signature
            0       5     0  this   Lcom/gl/Test;

  public static void main(java.lang.String[]);
    descriptor: ([Ljava/lang/String;)V
    flags: ACC_PUBLIC, ACC_STATIC
    Code:
      stack=2, locals=3, args_size=1
         0: new           #2                  // class java/util/ArrayList
         3: dup
         4: invokespecial #3                  // Method java/util/ArrayList."<init>":()V
         7: astore_1
         8: iconst_0
         9: istore_2
        10: iload_2
        11: bipush        10
        13: if_icmpge     33
        16: aload_1
        17: iload_2
        18: invokestatic  #4                  // Method java/lang/String.valueOf:(I)Ljava/lang/String;
        21: invokeinterface #5,  2            // InterfaceMethod java/util/List.add:(Ljava/lang/Object;)Z
        26: pop
        27: iinc          2, 1
        30: goto          10
        33: getstatic     #6                  // Field java/lang/System.err:Ljava/io/PrintStream;
        36: aload_1
        37: invokevirtual #7                  // Method java/lang/Object.toString:()Ljava/lang/String;
        40: invokevirtual #8                  // Method java/io/PrintStream.println:(Ljava/lang/String;)V
        43: return
      LineNumberTable:
        line 12: 0
        line 13: 8
        line 14: 16
        line 13: 27
        line 16: 33
        line 17: 43
      LocalVariableTable:
        Start  Length  Slot  Name   Signature
           10      23     2     i   I
            0      44     0  args   [Ljava/lang/String;
            8      36     1  list   Ljava/util/List;
      LocalVariableTypeTable:
        Start  Length  Slot  Name   Signature
            8      36     1  list   Ljava/util/List<Ljava/lang/String;>;
      StackMapTable: number_of_entries = 2
        frame_type = 253 /* append */
          offset_delta = 10
          locals = [ class java/util/List, int ]
        frame_type = 250 /* chop */
          offset_delta = 22
}
SourceFile: "Test.java"
```


上面是部分字节码，我呢个从LocalVariableTable中，能看到，类型是List，泛型信息没得了，但是我们能从LocalVariableTypeTable中，看到完成的信息，因此，我们是可以在运行时获取泛型的信息的。